MANIFEST.in
README.md
setup.py
abi/SarafanContent.json
abi/SarafanPeering.json
abi/SarafanToken.json
sarafan/__init__.py
sarafan/__main__.py
sarafan/app.py
sarafan/cli.py
sarafan/client.py
sarafan/distance.py
sarafan/download.py
sarafan/events.py
sarafan/logging_helpers.py
sarafan/magnet.py
sarafan/models.py
sarafan.egg-info/PKG-INFO
sarafan.egg-info/SOURCES.txt
sarafan.egg-info/dependency_links.txt
sarafan.egg-info/entry_points.txt
sarafan.egg-info/requires.txt
sarafan.egg-info/top_level.txt
sarafan/bundle/__init__.py
sarafan/bundle/bundle.py
sarafan/contract/__init__.py
sarafan/contract/abi.py
sarafan/contract/announcement_service.py
sarafan/contract/event_service.py
sarafan/contract/post_service.py
sarafan/contract/service.py
sarafan/database/__init__.py
sarafan/database/collections.py
sarafan/database/fields.py
sarafan/database/mappers.py
sarafan/database/migrations.py
sarafan/database/service.py
sarafan/ethereum/__init__.py
sarafan/ethereum/block_range.py
sarafan/ethereum/client.py
sarafan/ethereum/contract.py
sarafan/ethereum/event.py
sarafan/ethereum/exceptions.py
sarafan/onion/__init__.py
sarafan/onion/controller.py
sarafan/onion/service.py
sarafan/peering/__init__.py
sarafan/peering/client.py
sarafan/peering/peer_collection.py
sarafan/peering/service.py
sarafan/storage/__init__.py
sarafan/storage/service.py
sarafan/web/__init__.py
sarafan/web/handlers.py
sarafan/web/logging.py
sarafan/web/service.py
tests/__init__.py
tests/conftest.py
tests/factories.py
tests/test_app.py
tests/test_cli.py
tests/test_client.py
tests/test_download_service.py
tests/test_peering_service.py
tests/utils.py
tests/contract/__init__.py
tests/contract/test_contract_event_service.py
tests/contract/test_contract_service.py